kwchecker/__init__.py
kwchecker/kwchecker.py
kwchecker-1.1.0.dist-info/LICENSE.txt
kwchecker-1.1.0.dist-info/METADATA
kwchecker-1.1.0.dist-info/WHEEL
kwchecker-1.1.0.dist-info/top_level.txt
kwchecker-1.1.0.dist-info/RECORD
