Metadata-Version: 2.1
Name: kwchecker
Version: 1.1.0
Summary: A declarative verifier and sanitizer for python kwargs parameters.
Home-page: https://github.com/MoserMichael/kwchecker
Author: Michael Moser
Author-email: moser.michael@gmail.com
License: MIT
Keywords: utility
Platform: UNKNOWN
Classifier: Programming Language :: Python :: 3
Classifier: License :: OSI Approved :: MIT License
Classifier: Operating System :: OS Independent
Classifier: Topic :: Text Processing
Requires-Python: >=3.6
Requires-Dist: validate-email (==1.3)
